reactive/__init__.py
reactive/all_reactive.py
reactive/const.py
reactive/owner.py
reactive/property.py
ReactivePy-2.0.0.dev0.dist-info/LICENSE
ReactivePy-2.0.0.dev0.dist-info/METADATA
ReactivePy-2.0.0.dev0.dist-info/WHEEL
ReactivePy-2.0.0.dev0.dist-info/top_level.txt
ReactivePy-2.0.0.dev0.dist-info/RECORD
