Metadata-Version: 2.1
Name: ReactivePy
Version: 2.0.0.dev0
Summary: Reactive properties and owners for Python classes.
Home-page: https://github.com/Dan6erbond/ReactivePy
Author: Dan6erbond
Author-email: moravrav@gmail.com
License: GNU General Public License v3 (GPLv3)
Keywords: reactive python
Platform: UNKNOWN
Classifier: Development Status :: 4 - Beta
Classifier: Environment :: Console
Classifier: Intended Audience :: Developers
Classifier: License :: OSI Approved :: GNU General Public License v3 (GPLv3)
Classifier: Natural Language :: English
Classifier: Operating System :: OS Independent
Classifier: Programming Language :: Python :: 3.6
Classifier: Programming Language :: Python :: 3.7
Classifier: Programming Language :: Python :: 3.8
Classifier: Topic :: Education
Classifier: Topic :: Software Development :: Libraries :: Python Modules
Classifier: Topic :: Utilities
Classifier: Typing :: Typed
Requires-Python: >=3.6
